setup.py
cte_tree/__init__.py
cte_tree/models.py
cte_tree/tests.py
cte_tree/views.py
cte_tree_test/__init__.py
cte_tree_test/fields.py
cte_tree_test/models.py
cte_tree_test/tests.py
django_cte_trees.egg-info/PKG-INFO
django_cte_trees.egg-info/SOURCES.txt
django_cte_trees.egg-info/dependency_links.txt
django_cte_trees.egg-info/top_level.txt