Metadata-Version: 1.1
Name: django-cte-trees
Version: 0.9.2
Summary: Experimental implementation of Adjacency-List trees for Django using PostgreSQL Common Table Expressions (CTE).
Home-page: http://www.petrounias.org/software/django-cte-trees/
Author: Alexis Petrounias <www.petrounias.org>
Author-email: UNKNOWN
License: BSD
Download-URL: https://github.com/petrounias/django-cte-trees/archive/master.zip
Keywords: django,postgresql,cte,trees,sql
Platform: UNKNOWN
Classifier: Development Status :: 3 - Alpha
Classifier: Environment :: Web Environment
Classifier: Framework :: Django
Classifier: Intended Audience :: Developers
Classifier: License :: OSI Approved :: BSD License
Classifier: Operating System :: OS Independent
Classifier: Programming Language :: Python
Classifier: Topic :: Software Development :: Libraries :: Python Modules
